twodxPlay/__init__.py
twodxPlay/main.py
twodxPlay/twodx.py
2dxPlay-1.0.1.dist-info/LICENSE
2dxPlay-1.0.1.dist-info/METADATA
2dxPlay-1.0.1.dist-info/WHEEL
2dxPlay-1.0.1.dist-info/entry_points.txt
2dxPlay-1.0.1.dist-info/top_level.txt
2dxPlay-1.0.1.dist-info/RECORD
