Metadata-Version: 2.1
Name: 2dxPlay
Version: 1.0.1
Summary: Play a .2dx file.
Home-page: https://github.com/camprevail/2dxPlay
Author: camprevail
Author-email: cam.anderson573@gmail.com
License: MIT
Keywords: 2dx
Platform: UNKNOWN
Classifier: Programming Language :: Python :: 3
Classifier: License :: OSI Approved :: MIT License
Classifier: Operating System :: OS Independent
Requires-Dist: pygame
Requires-Dist: setuptools
